img2url/__init__.py
img2url/config.py
img2url/github.py
img2url/main.py
img2url/metadata.py
img2url/remotes/__init__.py
img2url/remotes/base.py
img2url/remotes/github.py
img2url/remotes/qiniu.py
img2url/remotes/utils.py
img2url-0.2.0.dist-info/DESCRIPTION.rst
img2url-0.2.0.dist-info/METADATA
img2url-0.2.0.dist-info/RECORD
img2url-0.2.0.dist-info/WHEEL
img2url-0.2.0.dist-info/entry_points.txt
img2url-0.2.0.dist-info/metadata.json
img2url-0.2.0.dist-info/top_level.txt
