Metadata-Version: 2.0
Name: img2url
Version: 0.2.0
Summary: upload image to github and return corresponding url.
Home-page: UNKNOWN
Author: huntzhan
Author-email: programmer.zhx@gmail.com
License: UNKNOWN
Platform: UNKNOWN
Classifier: License :: OSI Approved :: MIT License
Classifier: Development Status :: 1 - Planning
Classifier: Intended Audience :: Developers
Classifier: Topic :: Software Development :: Libraries
Classifier: Programming Language :: Python :: 2.7
Classifier: Programming Language :: Python :: 3.3
Classifier: Programming Language :: Python :: 3.4
Classifier: Programming Language :: Python :: 3.5
Requires-Dist: PyYAML
Requires-Dist: docopt
Requires-Dist: future
Requires-Dist: pyperclip
Requires-Dist: pysocks
Requires-Dist: qiniu
Requires-Dist: requests (>=2.10.0)
